ipclassifier/__init__.py
ipclassifier/__main__.py
ipclassifier/requirements.txt
ipclassifier/classifier/__init__.py
ipclassifier/classifier/classifier.py
ipclassifier/classifier/master_word_list.pickle
ipclassifier/classifier/model_base.py
ipclassifier/classifier/model_trainer.py
ipclassifier/classifier/models/ComplementNB-test-model.pickle
ipclassifier/classifier/models/MultinomialNB-test-model.pickle
ipclassifier/dataprep/__init__.py
ipclassifier/dataprep/processor.py
ipclassifier/iambic_line_processors/__init__.py
ipclassifier/iambic_line_processors/combinations_base.py
ipclassifier/iambic_line_processors/combinations_graph.py
ipclassifier/iambic_line_processors/graph_base.py
ipclassifier/iambic_line_processors/iambic_line.py
ipclassifier/nltk_data/corpora/cmudict/cmudict
ipclassifier/nltk_data/corpora/wordnet/adj.exc
ipclassifier/nltk_data/corpora/wordnet/adv.exc
ipclassifier/nltk_data/corpora/wordnet/citation.bib
ipclassifier/nltk_data/corpora/wordnet/cntlist.rev
ipclassifier/nltk_data/corpora/wordnet/data.adj
ipclassifier/nltk_data/corpora/wordnet/data.adv
ipclassifier/nltk_data/corpora/wordnet/data.noun
ipclassifier/nltk_data/corpora/wordnet/data.verb
ipclassifier/nltk_data/corpora/wordnet/index.adj
ipclassifier/nltk_data/corpora/wordnet/index.adv
ipclassifier/nltk_data/corpora/wordnet/index.noun
ipclassifier/nltk_data/corpora/wordnet/index.sense
ipclassifier/nltk_data/corpora/wordnet/index.verb
ipclassifier/nltk_data/corpora/wordnet/lexnames
ipclassifier/nltk_data/corpora/wordnet/noun.exc
ipclassifier/nltk_data/corpora/wordnet/verb.exc
ipclassifier/nltk_data/corpora/words/en
ipclassifier/nltk_data/taggers/averaged_perceptron_tagger/averaged_perceptron_tagger.pickle
ipclassifier/regularize/__init__.py
ipclassifier/regularize/regularize.py
ipclassifier/runners/__init__.py
ipclassifier/runners/classify_runner.py
ipclassifier/runners/feature_runner.py
ipclassifier/runners/train_runner.py
ipclassifier/syllabify/__init__.py
ipclassifier/syllabify/syllabify.py
ipclassifier-1.0.4.dist-info/LICENSE
ipclassifier-1.0.4.dist-info/METADATA
ipclassifier-1.0.4.dist-info/WHEEL
ipclassifier-1.0.4.dist-info/top_level.txt
ipclassifier-1.0.4.dist-info/RECORD
